static_website/__init__.py
static_website/static_website.py
romaincornuconsulting.static_website-0.0.5.dist-info/LICENCE
romaincornuconsulting.static_website-0.0.5.dist-info/METADATA
romaincornuconsulting.static_website-0.0.5.dist-info/WHEEL
romaincornuconsulting.static_website-0.0.5.dist-info/top_level.txt
romaincornuconsulting.static_website-0.0.5.dist-info/RECORD
