Metadata-Version: 2.1
Name: romaincornuconsulting.static-website
Version: 0.0.5
Summary: Static website
Home-page: UNKNOWN
Author: Romain CORNU
Author-email: consulting@romaincornu.com
License: UNKNOWN
Platform: UNKNOWN
Classifier: Programming Language :: Python :: 3
Requires-Python: >=3.6
Requires-Dist: aws-cdk.core
Requires-Dist: aws-cdk.aws-events
Requires-Dist: aws-cdk.aws-events-targets
Requires-Dist: aws-cdk.aws-certificatemanager
Requires-Dist: aws-cdk.aws-cloudfront
Requires-Dist: aws-cdk.aws-route53
Requires-Dist: aws-cdk.aws-route53-targets
Requires-Dist: aws-cdk.aws-s3
Requires-Dist: aws-cdk.aws-s3-deployment
